srf/__init__.py
srf/authentication.py
srf/cache.py
srf/constant.py
srf/converter.py
srf/exceptions.py
srf/export_import_view.py
srf/fields.py
srf/filters.py
srf/generics.py
srf/helpers.py
srf/mixins.py
srf/paginations.py
srf/permissions.py
srf/request.py
srf/routes.py
srf/serializers.py
srf/status.py
srf/utils.py
srf/validators.py
srf/views.py
srf/viewsets.py
srf_hdkj-0.6.1.dist-info/METADATA
srf_hdkj-0.6.1.dist-info/WHEEL
srf_hdkj-0.6.1.dist-info/top_level.txt
srf_hdkj-0.6.1.dist-info/RECORD
