Metadata-Version: 2.1
Name: srf-hdkj
Version: 0.6.1
Summary: sanic view Tool
Home-page: UNKNOWN
Author: hdkj
Author-email: 
License: UNKNOWN
Platform: UNKNOWN
Classifier: Programming Language :: Python :: 3
Classifier: Operating System :: OS Independent
Requires-Dist: ujson
Requires-Dist: openpyxl (==3.0.9)
Requires-Dist: sanic-jwt
